setup.py
apy/__init__.py
apy/authentication.py
apy/converters.py
apy/decorators.py
apy/util.py
apy.egg-info/PKG-INFO
apy.egg-info/SOURCES.txt
apy.egg-info/dependency_links.txt
apy.egg-info/requires.txt
apy.egg-info/top_level.txt