Metadata-Version: 1.0
Name: apy
Version: 0.2.1
Summary: Pythonic API development with flask
Home-page: https://github.com/stephenyoung/apy/wiki
Author: Stephen Young
Author-email: stephen@tryllo.com
License: UNKNOWN
Platform: UNKNOWN
